test_command_generation.py
wish_command_generation/__init__.py
wish_command_generation/exceptions.py
wish_command_generation/generator.py
wish_command_generation/graph.py
wish_command_generation/models.py
wish_command_generation/nodes/__init__.py
wish_command_generation/nodes/command_generation.py
wish_command_generation/nodes/rag.py
wish_command_generation/test_factories/__init__.py
wish_command_generation/test_factories/state_factory.py
wish_command_generation_api-0.6.28.dist-info/LICENSE
wish_command_generation_api-0.6.28.dist-info/METADATA
wish_command_generation_api-0.6.28.dist-info/WHEEL
wish_command_generation_api-0.6.28.dist-info/entry_points.txt
wish_command_generation_api/__init__.py
wish_command_generation_api/app.py
wish_command_generation_api/config.py
wish_command_generation_api/constants.py
wish_command_generation_api/core/__init__.py
wish_command_generation_api/core/generator.py
wish_command_generation_api/docs/divide_and_conquer.md
wish_command_generation_api/docs/fast_alternative_commands.md
wish_command_generation_api/docs/interactive_avoidance.md
wish_command_generation_api/docs/list_files.md
wish_command_generation_api/graph.py
wish_command_generation_api/models.py
wish_command_generation_api/nodes/__init__.py
wish_command_generation_api/nodes/command_generator.py
wish_command_generation_api/nodes/command_modifier.py
wish_command_generation_api/nodes/feedback_analyzer.py
wish_command_generation_api/nodes/network_error_handler.py
wish_command_generation_api/nodes/query_processor.py
wish_command_generation_api/nodes/result_formatter.py
wish_command_generation_api/nodes/timeout_handler.py
wish_command_generation_api-0.6.28.dist-info/RECORD
