Metadata-Version: 2.1
Name: wish-command-generation-api
Version: 0.6.28
Summary: Command generation API for wish
Keywords: wish,llm,ai,shell,command-generation
Author-Email: SecDevLab <dev@secdevlab.com>
Maintainer-Email: Sho Nakatani <lay.sakura@gmail.com>
License:                     GNU AFFERO GENERAL PUBLIC LICENSE
Classifier: Development Status :: 4 - Beta
Classifier: Intended Audience :: Developers
Classifier: Programming Language :: Python :: 3
Classifier: Programming Language :: Python :: 3.10
Classifier: Programming Language :: Python :: 3.11
Classifier: Programming Language :: Python :: 3.12
Classifier: Programming Language :: Python :: 3.13
Classifier: Topic :: Software Development :: Libraries
Classifier: Topic :: System :: Shells
Project-URL: Homepage, https://github.com/SecDev-Lab/wish
Project-URL: Documentation, https://github.com/SecDev-Lab/wish
Project-URL: Repository, https://github.com/SecDev-Lab/wish.git
Project-URL: Issues, https://github.com/SecDev-Lab/wish/issues
Requires-Python: >=3.10
Requires-Dist: pydantic>=2.10.6
Requires-Dist: langgraph>=0.3.5
Requires-Dist: langsmith>=0.3.11
Requires-Dist: langchain-openai>=0.3.9rc1
Requires-Dist: langchain-core>=0.3.41
Requires-Dist: langchain>=0.3.20
Requires-Dist: langchain-community>=0.1.0
Requires-Dist: pydantic-settings>=2.8.1
Requires-Dist: wish-models
Requires-Dist: wish-tools
Provides-Extra: chroma
Requires-Dist: chromadb>=0.4.22; extra == "chroma"
Provides-Extra: qdrant
Requires-Dist: langchain-qdrant>=0.2.0; extra == "qdrant"
Requires-Dist: qdrant-client>=1.7.0; extra == "qdrant"
